AUTHORS.rst
CHANGELOG.rst
LICENSE
MANIFEST.in
README.rst
setup.py
django_sites_groups.egg-info/PKG-INFO
django_sites_groups.egg-info/SOURCES.txt
django_sites_groups.egg-info/dependency_links.txt
django_sites_groups.egg-info/not-zip-safe
django_sites_groups.egg-info/requires.txt
django_sites_groups.egg-info/top_level.txt
sites_groups/__init__.py
sites_groups/admin.py
sites_groups/models.py
sites_groups/widgets.py
sites_groups/migrations/0001_initial.py
sites_groups/migrations/__init__.py