Metadata-Version: 1.1
Name: django-sites-groups
Version: 1.9.2
Summary: Organize sites from the Django sites framework into groups.
Home-page: http://github.com/praekelt/django-sites-groups
Author: Praekelt Consulting
Author-email: dev@praekelt.com
License: BSD
Platform: UNKNOWN
Classifier: Programming Language :: Python
Classifier: License :: OSI Approved :: BSD License
Classifier: Development Status :: 4 - Beta
Classifier: Operating System :: OS Independent
Classifier: Framework :: Django
Classifier: Intended Audience :: Developers
Classifier: Topic :: Internet :: WWW/HTTP :: Dynamic Content
